koios_api/__config__.py
koios_api/__init__.py
koios_api/account.py
koios_api/address.py
koios_api/asset.py
koios_api/block.py
koios_api/epoch.py
koios_api/library.py
koios_api/network.py
koios_api/ogmios.py
koios_api/pool.py
koios_api/script.py
koios_api/transactions.py
koios_api-1.1.0.1.dist-info/LICENSE
koios_api-1.1.0.1.dist-info/METADATA
koios_api-1.1.0.1.dist-info/WHEEL
koios_api-1.1.0.1.dist-info/top_level.txt
koios_api-1.1.0.1.dist-info/RECORD
