Metadata-Version: 2.1
Name: koios-api
Version: 1.1.0.1
Summary: A python package for the Cardano Blockchain Koios API (https://api.koios.rest/)
Author-email: APEX Stake Pool <cardanoapexpool@gmail.com>
Project-URL: Homepage, https://github.com/cardano-apexpool/koios-api-python
Project-URL: Bug Tracker, https://github.com/cardano-apexpool/koios-api-python/issues
Keywords: koios,cardano,blockchain,REST,API
Classifier: Programming Language :: Python :: 3
Classifier: License :: OSI Approved :: MIT License
Classifier: Operating System :: OS Independent
Requires-Python: >=3.7
License-File: LICENSE
Requires-Dist: requests >=2.20.0
